signal2html/__init__.py
signal2html/__main__.py
signal2html/__version__.py
signal2html/addressbook.py
signal2html/core.py
signal2html/dbproto.py
signal2html/exceptions.py
signal2html/html.py
signal2html/html_colors.py
signal2html/linkify.py
signal2html/models.py
signal2html/types.py
signal2html/ui.py
signal2html/versioninfo.py
signal2html/templates/thread.html
signal2html-0.2.11.dist-info/LICENSE
signal2html-0.2.11.dist-info/METADATA
signal2html-0.2.11.dist-info/WHEEL
signal2html-0.2.11.dist-info/entry_points.txt
signal2html-0.2.11.dist-info/top_level.txt
signal2html-0.2.11.dist-info/RECORD
