Metadata-Version: 2.1
Name: signal2html
Version: 0.2.11
Summary: Convert your Signal backup to pretty HTML
Home-page: https://github.com/GjjvdBurg/signal2html
Author: Gertjan van den Burg
Author-email: gertjanvandenburg@gmail.com
License: MIT
Classifier: License :: OSI Approved :: MIT License
Classifier: Programming Language :: Python
Classifier: Programming Language :: Python :: 3
Classifier: Programming Language :: Python :: 3.6
Classifier: Programming Language :: Python :: Implementation :: CPython
Classifier: Programming Language :: Python :: Implementation :: PyPy
Requires-Python: >=3.6.0
License-File: LICENSE
Requires-Dist: emoji (>=2.0)
Requires-Dist: jinja2
Requires-Dist: pure-protobuf
Requires-Dist: linkify-it-py
Requires-Dist: dataclasses ; python_version == "3.6"
Provides-Extra: dev
Requires-Dist: green ; extra == 'dev'
Requires-Dist: black ; extra == 'dev'
Requires-Dist: isort ; extra == 'dev'
Provides-Extra: docs
Provides-Extra: tests
